{
  "$schema": "https://developer.microsoft.com/json-schemas/fabric/item/report/definition/bookmark/1.3.0/schema.json",
  "displayName": "Mensal",
  "name": "58e1579909e77e58809d",
  "options": {
    "targetVisualNames": [
      "ecaf3dab5adb43cb6342"
    ],
    "suppressData": true
  },
  "explorationState": {
    "version": "1.3",
    "activeSection": "ddc417a050a4793d7900",
    "sections": {
      "ddc417a050a4793d7900": {
        "visualContainers": {
          "0e9962c9e7264ea7101e": {
            "filters": {
              "byExpr": [
                {
                  "name": "ca51d1aa4317dbe78d5a",
                  "type": "Advanced",
                  "expression": {
                    "Measure": {
                      "Expression": {
                        "SourceRef": {
                          "Entity": "Medidas"
                        }
                      },
                      "Property": "mMargemContribuicao"
                    }
                  },
                  "howCreated": 0
                }
              ]
            },
            "singleVisual": {
              "visualType": "card",
              "objects": {},
              "orderBy": [
                {
                  "Direction": 2,
                  "Expression": {
                    "Measure": {
                      "Expression": {
                        "SourceRef": {
                          "Entity": "Medidas"
                        }
                      },
                      "Property": "mMargemContribuicao"
                    }
                  }
                }
              ]
            }
          },
          "2d64cde2fceb0b2743bb": {
            "filters": {
              "byExpr": [
                {
                  "name": "90c83fcd3d8390dd197d",
                  "type": "Advanced",
                  "expression": {
                    "Column": {
                      "Expression": {
                        "SourceRef": {
                          "Entity": "dCalendario"
                        }
                      },
                      "Property": "Ano"
                    }
                  },
                  "howCreated": 0
                },
                {
                  "name": "2b02097c87612d3fc39a",
                  "type": "Categorical",
                  "expression": {
                    "Column": {
                      "Expression": {
                        "SourceRef": {
                          "Entity": "dCalendario"
                        }
                      },
                      "Property": "TrimestreNome"
                    }
                  },
                  "howCreated": 0
                },
                {
                  "name": "4bba11f6cc207307e36b",
                  "type": "Categorical",
                  "expression": {
                    "Column": {
                      "Expression": {
                        "SourceRef": {
                          "Entity": "dCalendario"
                        }
                      },
                      "Property": "MesNomeAbreviado"
                    }
                  },
                  "howCreated": 0
                },
                {
                  "name": "d51bc9e1dd377930dab1",
                  "type": "Advanced",
                  "expression": {
                    "Measure": {
                      "Expression": {
                        "SourceRef": {
                          "Entity": "Medidas"
                        }
                      },
                      "Property": "mReceita"
                    }
                  },
                  "howCreated": 0
                },
                {
                  "name": "99811ab11afcbd4b4a57",
                  "type": "Advanced",
                  "expression": {
                    "Measure": {
                      "Expression": {
                        "SourceRef": {
                          "Entity": "Medidas"
                        }
                      },
                      "Property": "mReceitaLY"
                    }
                  },
                  "howCreated": 0
                }
              ]
            },
            "singleVisual": {
              "visualType": "clusteredColumnChart",
              "objects": {},
              "activeProjections": {
                "Category": [
                  {
                    "Column": {
                      "Expression": {
                        "SourceRef": {
                          "Entity": "dCalendario"
                        }
                      },
                      "Property": "Ano"
                    }
                  },
                  {
                    "Column": {
                      "Expression": {
                        "SourceRef": {
                          "Entity": "dCalendario"
                        }
                      },
                      "Property": "TrimestreNome"
                    }
                  },
                  {
                    "Column": {
                      "Expression": {
                        "SourceRef": {
                          "Entity": "dCalendario"
                        }
                      },
                      "Property": "MesNomeAbreviado"
                    }
                  }
                ]
              }
            }
          },
          "336e5600c7ebb524e8be": {
            "singleVisual": {
              "visualType": "actionButton",
              "objects": {}
            }
          },
          "4ab95d2c36138318c8c8": {
            "filters": {
              "byExpr": [
                {
                  "name": "c77d91cdd471d8f9ccff",
                  "type": "Advanced",
                  "expression": {
                    "Measure": {
                      "Expression": {
                        "SourceRef": {
                          "Entity": "Medidas"
                        }
                      },
                      "Property": "mDespesas"
                    }
                  },
                  "howCreated": 0
                }
              ]
            },
            "singleVisual": {
              "visualType": "card",
              "objects": {},
              "orderBy": [
                {
                  "Direction": 2,
                  "Expression": {
                    "Measure": {
                      "Expression": {
                        "SourceRef": {
                          "Entity": "Medidas"
                        }
                      },
                      "Property": "mDespesas"
                    }
                  }
                }
              ]
            }
          },
          "ae77184a995f76a9c80a": {
            "filters": {
              "byExpr": [
                {
                  "name": "2a2698ceddb6d192da32",
                  "type": "Categorical",
                  "expression": {
                    "Column": {
                      "Expression": {
                        "SourceRef": {
                          "Entity": "dPlanoContas"
                        }
                      },
                      "Property": "Conta Nível 3"
                    }
                  },
                  "howCreated": 0
                },
                {
                  "name": "d4647b2ae405daf141b5",
                  "type": "Advanced",
                  "expression": {
                    "Measure": {
                      "Expression": {
                        "SourceRef": {
                          "Entity": "Medidas"
                        }
                      },
                      "Property": "mReceita"
                    }
                  },
                  "howCreated": 0
                }
              ]
            },
            "singleVisual": {
              "visualType": "clusteredBarChart",
              "objects": {},
              "orderBy": [
                {
                  "Direction": 2,
                  "Expression": {
                    "Measure": {
                      "Expression": {
                        "SourceRef": {
                          "Entity": "Medidas"
                        }
                      },
                      "Property": "mReceita"
                    }
                  }
                }
              ],
              "activeProjections": {
                "Category": [
                  {
                    "Column": {
                      "Expression": {
                        "SourceRef": {
                          "Entity": "dPlanoContas"
                        }
                      },
                      "Property": "Conta Nível 3"
                    }
                  }
                ]
              }
            }
          },
          "b3902788884a4b5cd688": {
            "filters": {
              "byName": {
                "ed57fc27fb14627bd556": {
                  "name": "ed57fc27fb14627bd556",
                  "type": "Categorical",
                  "filter": {
                    "Version": 2,
                    "From": [
                      {
                        "Name": "d",
                        "Entity": "dCalendario",
                        "Type": 0
                      }
                    ],
                    "Where": [
                      {
                        "Condition": {
                          "In": {
                            "Expressions": [
                              {
                                "Column": {
                                  "Expression": {
                                    "SourceRef": {
                                      "Source": "d"
                                    }
                                  },
                                  "Property": "Ano"
                                }
                              }
                            ],
                            "Values": [
                              [
                                {
                                  "Literal": {
                                    "Value": "2017L"
                                  }
                                }
                              ],
                              [
                                {
                                  "Literal": {
                                    "Value": "2018L"
                                  }
                                }
                              ],
                              [
                                {
                                  "Literal": {
                                    "Value": "2019L"
                                  }
                                }
                              ]
                            ]
                          }
                        }
                      }
                    ]
                  },
                  "expression": {
                    "Column": {
                      "Expression": {
                        "SourceRef": {
                          "Entity": "dCalendario"
                        }
                      },
                      "Property": "Ano"
                    }
                  },
                  "howCreated": 1
                }
              },
              "byExpr": [
                {
                  "name": "1c39982ab578b62d3291",
                  "type": "Categorical",
                  "expression": {
                    "Column": {
                      "Expression": {
                        "SourceRef": {
                          "Entity": "dCalendario"
                        }
                      },
                      "Property": "MesNome"
                    }
                  },
                  "howCreated": 0
                }
              ]
            },
            "singleVisual": {
              "visualType": "slicer",
              "objects": {
                "merge": {
                  "data": [
                    {
                      "properties": {
                        "mode": {
                          "expr": {
                            "Literal": {
                              "Value": "'Dropdown'"
                            }
                          }
                        }
                      }
                    }
                  ]
                }
              },
              "activeProjections": {
                "Values": [
                  {
                    "Column": {
                      "Expression": {
                        "SourceRef": {
                          "Entity": "dCalendario"
                        }
                      },
                      "Property": "MesNome"
                    }
                  }
                ]
              }
            }
          },
          "b66fec9fb77070eb2279": {
            "filters": {
              "byExpr": [
                {
                  "name": "22c45e0eca337686a40a",
                  "type": "Advanced",
                  "expression": {
                    "Measure": {
                      "Expression": {
                        "SourceRef": {
                          "Entity": "Medidas"
                        }
                      },
                      "Property": "mReceita"
                    }
                  },
                  "howCreated": 0
                }
              ]
            },
            "singleVisual": {
              "visualType": "card",
              "objects": {},
              "orderBy": [
                {
                  "Direction": 2,
                  "Expression": {
                    "Measure": {
                      "Expression": {
                        "SourceRef": {
                          "Entity": "Medidas"
                        }
                      },
                      "Property": "mReceita"
                    }
                  }
                }
              ]
            }
          },
          "daa3f07db27ab71a2915": {
            "filters": {
              "byExpr": [
                {
                  "name": "b5df5a7334a161b55382",
                  "type": "Categorical",
                  "expression": {
                    "Column": {
                      "Expression": {
                        "SourceRef": {
                          "Entity": "dPlanoContas"
                        }
                      },
                      "Property": "Conta Nível 3"
                    }
                  },
                  "howCreated": 0
                },
                {
                  "name": "e8c818133164bda5a1ee",
                  "type": "Advanced",
                  "expression": {
                    "Measure": {
                      "Expression": {
                        "SourceRef": {
                          "Entity": "Medidas"
                        }
                      },
                      "Property": "mReceita"
                    }
                  },
                  "howCreated": 0
                }
              ]
            },
            "singleVisual": {
              "visualType": "tableEx",
              "objects": {},
              "orderBy": [
                {
                  "Direction": 2,
                  "Expression": {
                    "Measure": {
                      "Expression": {
                        "SourceRef": {
                          "Entity": "Medidas"
                        }
                      },
                      "Property": "mReceita"
                    }
                  }
                }
              ],
              "display": {
                "mode": "hidden"
              }
            }
          },
          "e5e699348a3533e262d7": {
            "filters": {
              "byName": {
                "ed57fc27fb14627bd556": {
                  "name": "ed57fc27fb14627bd556",
                  "type": "Categorical",
                  "filter": {
                    "Version": 2,
                    "From": [
                      {
                        "Name": "d",
                        "Entity": "dCalendario",
                        "Type": 0
                      }
                    ],
                    "Where": [
                      {
                        "Condition": {
                          "In": {
                            "Expressions": [
                              {
                                "Column": {
                                  "Expression": {
                                    "SourceRef": {
                                      "Source": "d"
                                    }
                                  },
                                  "Property": "Ano"
                                }
                              }
                            ],
                            "Values": [
                              [
                                {
                                  "Literal": {
                                    "Value": "2017L"
                                  }
                                }
                              ],
                              [
                                {
                                  "Literal": {
                                    "Value": "2018L"
                                  }
                                }
                              ],
                              [
                                {
                                  "Literal": {
                                    "Value": "2019L"
                                  }
                                }
                              ]
                            ]
                          }
                        }
                      }
                    ]
                  },
                  "expression": {
                    "Column": {
                      "Expression": {
                        "SourceRef": {
                          "Entity": "dCalendario"
                        }
                      },
                      "Property": "Ano"
                    }
                  },
                  "howCreated": 0
                }
              }
            },
            "singleVisual": {
              "visualType": "slicer",
              "objects": {
                "merge": {
                  "general": [
                    {
                      "properties": {
                        "filter": {
                          "filter": {
                            "Version": 2,
                            "From": [
                              {
                                "Name": "d",
                                "Entity": "dCalendario",
                                "Type": 0
                              }
                            ],
                            "Where": [
                              {
                                "Condition": {
                                  "In": {
                                    "Expressions": [
                                      {
                                        "Column": {
                                          "Expression": {
                                            "SourceRef": {
                                              "Source": "d"
                                            }
                                          },
                                          "Property": "Ano"
                                        }
                                      }
                                    ],
                                    "Values": [
                                      [
                                        {
                                          "Literal": {
                                            "Value": "2018L"
                                          }
                                        }
                                      ]
                                    ]
                                  }
                                }
                              }
                            ]
                          }
                        }
                      }
                    }
                  ],
                  "data": [
                    {
                      "properties": {
                        "mode": {
                          "expr": {
                            "Literal": {
                              "Value": "'Dropdown'"
                            }
                          }
                        }
                      }
                    }
                  ],
                  "selection": [
                    {
                      "properties": {
                        "strictSingleSelect": {
                          "expr": {
                            "Literal": {
                              "Value": "true"
                            }
                          }
                        }
                      }
                    }
                  ]
                }
              },
              "activeProjections": {
                "Values": [
                  {
                    "Column": {
                      "Expression": {
                        "SourceRef": {
                          "Entity": "dCalendario"
                        }
                      },
                      "Property": "Ano"
                    }
                  }
                ]
              }
            }
          },
          "fc0f6dff7b1159538142": {
            "singleVisual": {
              "visualType": "actionButton",
              "objects": {}
            }
          },
          "91fd80aa6af4483520d4": {
            "filters": {
              "byExpr": [
                {
                  "name": "65057d7a0e317fcd3e35",
                  "type": "Advanced",
                  "expression": {
                    "Column": {
                      "Expression": {
                        "SourceRef": {
                          "Entity": "dCalendario"
                        }
                      },
                      "Property": "Ano"
                    }
                  },
                  "howCreated": 0
                },
                {
                  "name": "07c8f8f7954cf2e60e4f",
                  "type": "Categorical",
                  "expression": {
                    "Column": {
                      "Expression": {
                        "SourceRef": {
                          "Entity": "dCalendario"
                        }
                      },
                      "Property": "TrimestreNome"
                    }
                  },
                  "howCreated": 0
                },
                {
                  "name": "6471ee30705a9ddda190",
                  "type": "Categorical",
                  "expression": {
                    "Column": {
                      "Expression": {
                        "SourceRef": {
                          "Entity": "dCalendario"
                        }
                      },
                      "Property": "MesNomeAbreviado"
                    }
                  },
                  "howCreated": 0
                },
                {
                  "name": "ec8b0c75a85f7d2650eb",
                  "type": "Advanced",
                  "expression": {
                    "Measure": {
                      "Expression": {
                        "SourceRef": {
                          "Entity": "Medidas"
                        }
                      },
                      "Property": "mReceitaAcum"
                    }
                  },
                  "howCreated": 0
                }
              ]
            },
            "singleVisual": {
              "visualType": "columnChart",
              "objects": {},
              "activeProjections": {
                "Category": [
                  {
                    "Column": {
                      "Expression": {
                        "SourceRef": {
                          "Entity": "dCalendario"
                        }
                      },
                      "Property": "Ano"
                    }
                  },
                  {
                    "Column": {
                      "Expression": {
                        "SourceRef": {
                          "Entity": "dCalendario"
                        }
                      },
                      "Property": "TrimestreNome"
                    }
                  },
                  {
                    "Column": {
                      "Expression": {
                        "SourceRef": {
                          "Entity": "dCalendario"
                        }
                      },
                      "Property": "MesNomeAbreviado"
                    }
                  }
                ]
              },
              "display": {
                "mode": "hidden"
              }
            }
          },
          "d7f329c6ba8de0ef44aa": {
            "singleVisual": {
              "visualType": "actionButton",
              "objects": {}
            }
          },
          "ecaf3dab5adb43cb6342": {
            "singleVisual": {
              "visualType": "actionButton",
              "objects": {}
            }
          }
        }
      }
    },
    "objects": {
      "merge": {
        "outspacePane": [
          {
            "properties": {
              "expanded": {
                "expr": {
                  "Literal": {
                    "Value": "false"
                  }
                }
              }
            }
          }
        ]
      }
    }
  }
}